MANIFEST.in
README.rst
setup.py
docs/HISTORY.txt
transmogrify/__init__.py
transmogrify.regexp.egg-info/PKG-INFO
transmogrify.regexp.egg-info/SOURCES.txt
transmogrify.regexp.egg-info/dependency_links.txt
transmogrify.regexp.egg-info/entry_points.txt
transmogrify.regexp.egg-info/namespace_packages.txt
transmogrify.regexp.egg-info/top_level.txt
transmogrify/regexp/__init__.py
transmogrify/regexp/configure.zcml