Metadata-Version: 1.0
Name: transmogrify.regexp
Version: 0.3.0
Summary: Modify key values by applying a regular expression
Home-page: https://github.com/aclark4life/transmogrify.regexp
Author: UNKNOWN
Author-email: UNKNOWN
License: UNKNOWN
Platform: UNKNOWN
